tunepy/TunepyGUI.py
tunepy/__init__.py
tunepy/tunable.py
tunepy/tunepy.py
tunepy/widgets.py
tunepy-1.1.dist-info/DESCRIPTION.rst
tunepy-1.1.dist-info/METADATA
tunepy-1.1.dist-info/RECORD
tunepy-1.1.dist-info/WHEEL
tunepy-1.1.dist-info/metadata.json
tunepy-1.1.dist-info/top_level.txt
